{
  "Id": "27bf81ff-ee60-4fd3-b757-d53f91a8dbc9",
  "Name": "Bethlehem Ster B-mol",
  "Key": 7,
  "TimeSignature": 0,
  "ChorusText": "Bethlehem ster wil ook vir my\nNa die Jesus kind toe lei\nWant ek soek en km van ver\nBethlehem Ster, o lieflike Ster!        X2\nRefrein:\nBethlehem Ster, lieflike Ster\nLeidsman na Jesus, o lieflike, lieflike Ster!\nBethlehem\nSter B-mol\nBethlehem Ster, o wonderlik\nHeerlik, lieflike gesig!\nWyse manne kom van ver\nBethlehem\nSter, o lieflike Ster!       X2\nRefrein:\nBethlehem Ster, lieflike Ster\nLeidsman na Jesus, o lieflike, lieflike Ster!\nBethlehem Ster, Gods liefdelig\nWat ons pad na Jesus rig\nLei die kinders ook van ver\nLei\nhul na Jesus, lieflike Ster!         X2\nRefrein:\nBethlehem Ster, lieflike Ster\nLeidsman na Jesus, o lieflike, lieflike Ster!\nBethlehem Ster, so wonderskoon\nLigstraal van die hemeltroon\nLig vir heid\u2019ne heinde en ver\nBethlehem Ster, o lieflike Ster!        X2\nRefrein:\nBethlehem Ster, lieflike Ster\nLeidsman na Jesus, o lieflike, lieflike Ster!",
  "Type": 0
}