{
  "Id": "5669418d-4152-46ed-890c-d7c4e0ae730f",
  "Name": "This The Air That I Breathe",
  "Key": 6,
  "TimeSignature": 0,
  "ChorusText": "And I\u2026\u2026I\u2019m desperate for you\nAnd I\u2026\u2026I\u2019m desperate for you\nAnd I\u2026\u2026I\u2019m lost without you\nAnd I\u2026\u2026I\u2019m lost without you\nThis is the air I breathe\nThis is the air I breathe\nYour Holy pre\u2014sence\nLiving   -- in me\nThis is my daily bread\nThis is my daily bread\nYou\u2019re every w\u2014ord\nSpoken  -- to me",
  "Type": 0
}