{
  "Id": "5b43de35-2173-4081-9140-60d837881f19",
  "Name": "15Nov2009",
  "Key": 0,
  "TimeSignature": 0,
  "ChorusText": "O my siel wees bly, jou Verlosser is naby\nEn die hemelse kleed sal jy dra\nWees getrou en waak, hou jou klere rein\nwant die koms van die Here is naby\nd\naar sal glorie wees in die hemel\nin die heerlike lig van\nSy\naangesig\nas my Jesus kom\n,\nHalleluJaH\nx2\nKom ons loof die Heer\nsaam met die engeleskaar\nHy is in die hemel\nen my hart is daar\nLet it rain, let it rain\nOpen the flood gates of heaven\nLet it rain, let it rain\nopen the flood gates of heaven\n7\nWe are standing on\nHoly\nground\nWe\nare\nstanding\non\nHoly ground\nand\nI know that\nthere\nare\nangels all around\nLet\u2019s  just\npraise Jesus now\nfor we are standing in His\npresence\non\nHoly ground\nRondom\nJerusalem is\nberge\nso\nbeskerm die Here Sy\nvolk\t    x2\nHy beskerm ons van agter en van voor af\nSo beskerm die Here Sy\nvolk\nRondom Jerusalem is\nberge,\nso\nbeskerm die Here Sy volk\nWonderful, wonderful Jesus is to me,\nCounselor, mighty God, Prince of peace is He\nSaving me, keeping me, from all sin and shame\nWonderful is my Redeemer, praise His Name",
  "Type": 0
}