{
  "Id": "b66906c0-dbf1-4168-96de-941db0c5372c",
  "Name": "Im gonna run run run",
  "Key": 3,
  "TimeSignature": 0,
  "ChorusText": "I\u2019m gonna run\nI\u2019m gonna run, run, run to see my Jesus\nI\u2019m gonna run, run, run to see my Jesus\nI\u2019m gonna run, run, run to see my Jesus\nwhen He comes, when He comes\nevery knee shall bow before Him\nevery knee shall bow before Him\nevery knee shall bow before Him\nwhen He comes, when He comes\nevery eye shall then behold Him\nevery eye shall then behold Him\nevery eye shall then behold Him\nwhen He comes when He comes",
  "Type": 0
}