{
  "id": "38f28920-bab1-4902-85e6-ffaec78b437e",
  "name": "Die Hemel Se Poort Staan Oop",
  "chorusText": "Die hemel, die hemel\ndie hemel se poort staan oop\nEk wil nie voor die poort staan nie x2\nEk wil ingaan, ek wil ingaan\nEk wil nie voor die poort staan nie\nJy hoef nie voor die poort te staan nie x2\nJy kan ingaan, jy kan ingaan\nJy hoef nie voor die poort te staan nie",
  "key": 8,
  "type": 0,
  "timeSignature": 0,
  "createdAt": "2025-07-17T15:02:42.946544Z",
  "metadata": {},
  "domainEvents": []
}