{
  "id": "46295722-99da-4ac0-bd05-d2895e00ab60",
  "name": "Open The Eyes Of My Heart Lord",
  "chorusText": "Open the eyes of my heart\nI want to see you\nI want to see you\n1 of 3\nTo see You high and lifted up\nShining in the light of Your glory\nPour out Your power and love\nAs we sing holy, holy, holy \n2 of 3\nHoly, Holy, Holy\nHoly, Holy, Holy\nHoly, Holy, Holy\nI want to see you\n3 of 3",
  "key": 0,
  "type": 0,
  "timeSignature": 0,
  "createdAt": "2025-07-17T15:02:15.020446Z",
  "metadata": {},
  "domainEvents": []
}