{
  "id": "5831fdea-6729-4faa-8f28-68692bf16474",
  "name": "How Great Is Our God(remix)",
  "chorusText": "How Great Is Our God\nThe splendour of the King, \nClothed in Majesty\nLet all the earth rejoice, \nall the earth rejoice\nHe wraps Himself in light \nAnd darkness tries to hide\nAnd trenbles at his voice, \ntrembles at His voice\nHow Great, is our God,\nSing with me how Great, is our God\nAnd all will see how Great, \nHow Great, is our God\nAge to age He stands \nAnd time is in His hands\nBeginning and the end (2x)\nOur God is only one\nFather, Spirit, Son\nThe lion and the lamb (2x)\nYou\u2019re the name above all names,\nWorthy of all praise\nMy heart will sing, \u201CHow Great, is our God\u201D\n\nThen sings my soul, My Saviour, God to Thee-\nHow Great Thou art \nHow Great Thou art\nThen sings my soul, My Saviour, God to Thee\nHow Great Thou art, how Great, Thou art",
  "key": 0,
  "type": 0,
  "timeSignature": 0,
  "createdAt": "2025-07-17T15:24:10.148256Z",
  "metadata": {},
  "domainEvents": []
}