{
  "id": "6034aafd-adbc-431e-94bd-4750579c2430",
  "name": "We Exalt Thee\u002Bafr",
  "chorusText": "We ex-alt Thee\nWe ex-alt Thee\n                  o-ho Lord\u2026                     (repeat)\nFor you alone are Holy\nYou alone are worthy,\nYou deserve the glory\nJesus You alone\nONS AANBID UONS AANBID UONS AANBID U             GROTE HEER   (HERHAAL)U ALLEEN IS HEILIGU ALLEEN IS WAARDIGU VERDIEN DIE GLORIEJESUS U ALLEEN",
  "key": 0,
  "type": 0,
  "timeSignature": 0,
  "createdAt": "2025-07-16T06:20:44.487225Z",
  "metadata": {},
  "domainEvents": []
}