{
  "id": "cff38f92-ca03-4eaf-95bd-d17b43367a0b",
  "name": "Worthy Of Glory And Worthy Of Honour",
  "chorusText": "Worthy of glory and worthy of honour and worthy of praise is He\nWorthy of glory and worthy of honour and worthy of praise is He\n\nHe has redeemed me by the blood of the Lamb\nHe set my spirit free\nworthy of glory and worthy of honour and\nworthy of praise is He",
  "key": 0,
  "type": 0,
  "timeSignature": 0,
  "createdAt": "2025-07-16T14:51:19.072997Z",
  "metadata": {},
  "domainEvents": []
}